{
  "visualization": {
    "config": [
      4, 4, 7, 4, 4, 7, 4, 4, 7, 4, 4, 7, 4, 4, 7, 4, 4, 0, 4, 4, 7, 4, 4, 7, 4, 4, 7, 4, 4, 7, 4, 4, 7, 4, 4, 7, 5, 7,
      7, 4, 4, 7, 4, 4, 7, 4, 4, 7, 4, 4, 7, 4, 4, 7, 4, 4, 7, 4, 4, 7, 4, 4, 1, 4, 4, 7, 4, 4, 7, 4, 4, 7, 4, 4, 7, 4,
      4, 7, 4, 4, 7, 4, 4, 7, 4, 4, 7, 4, 4, 7, 4, 4, 7, 4, 4, 7, 4, 4, 7, 4, 4, 7, 4, 4, 7, 4, 4, 1, 4, 4, 7, 4, 4, 7,
      4, 4, 7, 4, 4, 7, 4, 4, 7, 4, 4, 7, 4, 4, 7, 4, 4, 7, 4, 4, 7, 4, 4, 7, 4, 4, 7, 4, 4, 7, 4, 4, 7, 4, 4, 7, 4, 4,
      7, 4, 4, 7, 4, 4, 7, 6, 4, 1, 4, 4, 1, 4, 4, 7, 4, 4, 7, 4, 4, 7, 4, 4, 7, 4, 4, 7, 4, 4, 7, 4, 4, 7, 4, 4, 7, 4,
      4, 7, 4, 4, 7, 4, 4, 7, 4, 4, 7, 4, 4, 1, 4, 4, 7, 4, 4, 7, 4, 4, 7, 4, 4, 7, 4, 4, 7, 4, 4, 7, 4, 4, 7, 4, 4, 7,
      4, 4, 7, 4, 4, 7, 4, 4, 7, 4, 4, 7, 4, 4, 7, 4, 4, 7, 4, 4, 7, 4, 4, 7, 4, 4, 7, 4, 4, 7, 4, 4, 7, 4, 4, 7, 4, 4,
      7, 4, 4, 7, 4, 4, 1, 4, 4, 7, 4, 4, 7, 4, 4, 7, 4, 4, 7, 4, 4, 1, 4, 4, 7, 4, 4, 7, 4, 4, 7, 4, 4, 7, 4, 4, 7, 4,
      4, 7, 4, 4, 7, 4, 4, 7, 4, 4, 1, 4, 4, 7, 4, 4, 7, 4, 4, 7, 4, 4, 7, 5, 4, 7, 4, 4, 7, 4, 4, 7, 4, 4, 7, 4, 4, 7,
      4, 4, 7, 4, 4, 1, 4, 4, 7, 4, 4, 7, 4, 4, 7, 4, 4, 7, 4, 4, 7, 4, 4, 7, 4, 4, 7, 4, 4, 7, 4, 4, 1, 4, 4, 7, 4, 4,
      7, 4, 4, 7, 4, 4, 7, 4, 4, 7, 4, 4, 7, 4, 4, 7, 4, 4, 7, 4, 4, 7, 4, 4, 7, 4, 4, 7, 4, 4, 7, 4, 4, 7, 4, 4, 7, 4,
      4, 7, 4, 4, 7, 4, 4, 7, 4, 4, 7, 4, 4, 7, 4, 4, 7, 4, 4, 7, 4, 4, 7, 5, 4, 7, 4, 4, 7, 4, 4, 7, 4, 4, 7, 4, 4, 7,
      4, 4, 1, 4, 4, 7, 4, 4, 7, 4, 4, 7, 4, 4, 7, 4, 4, 7, 4, 4, 7, 4, 4, 7, 4, 4, 7, 4, 4, 7, 4, 4, 7, 4, 4, 7, 4, 4,
      7, 4, 4, 7, 4, 4, 1, 4, 4, 7, 4, 4, 7, 4, 4, 7, 4, 4, 7, 4, 4, 7, 4, 4, 7, 4, 4, 7, 4, 4, 7, 4, 4, 7, 4, 4, 7, 4,
      4, 7, 4, 4, 7, 4, 4, 7, 4, 4, 7, 4, 4, 7, 4, 4, 7, 4, 4, 7, 4, 4, 7, 4, 4, 7, 4, 7, 7, 4, 4, 7, 4, 4, 7, 4, 4, 7,
      4, 4, 7, 4, 4, 7, 4, 4, 7, 4, 4, 7, 4, 4, 7, 4, 4, 7, 4, 4, 7, 4, 4, 7, 4, 4, 7, 4, 4, 7, 4, 4, 7, 4, 4, 1, 4, 4,
      7, 4, 4, 7, 4, 4, 7, 4, 4, 7, 4, 7, 7, 4, 4, 7, 4, 4, 7, 4, 4, 7, 4, 4, 7, 4, 4, 7, 4, 4, 7, 4, 4, 7, 4, 4, 7, 4,
      4, 7, 4, 4, 7, 4, 4, 7, 4, 4, 7, 4, 4, 7, 4, 4, 7, 4, 4, 7, 4, 4, 7, 4, 4, 7, 4, 4, 7, 4, 4, 7, 4, 4, 7, 4, 4, 7,
      4, 4, 1, 4, 4, 7, 4, 4, 7, 4, 4, 7, 4, 4, 7, 4, 4, 7, 4, 4, 7, 4, 4, 7, 4, 4, 7, 4, 4, 7, 4, 4, 7, 4, 4, 7, 4, 4,
      7, 4, 4, 7, 4, 4, 7, 4, 4, 7, 4, 4, 7, 4, 4, 7, 4, 4, 7, 4, 4, 1, 4, 4, 7, 4, 4, 1, 4, 4, 7, 4, 4, 7, 4, 4, 7, 4,
      4, 7, 4, 4, 7, 4, 4, 7, 4, 4, 7, 4, 4, 7, 4, 4, 7, 4, 4, 7, 4, 4, 7, 4, 4, 7, 4, 4, 7, 4, 4, 7, 4, 4, 7, 4, 4, 7,
      4, 4, 7, 4, 4, 0, 4, 4, 1, 4, 4, 7, 4, 4, 7, 4, 4, 7, 4, 4, 7, 4, 4, 7, 4, 4, 7, 4, 4, 7, 4, 4, 7, 4, 4, 7, 4, 4,
      1, 4, 4, 7, 4, 4, 7, 4, 4, 7, 4, 4, 7, 4, 4, 1, 4, 4, 7, 4, 4, 7, 4, 4, 7, 4, 4, 7, 4, 4, 7, 4, 4, 7, 4, 4, 7, 4,
      4, 7, 4, 4, 7, 4, 4, 7, 4, 4, 7, 4, 4, 7, 4, 4, 7, 4, 4, 7, 4, 4, 1, 4, 4, 7, 4, 4, 7, 4, 4, 7, 4, 4, 7, 4, 4, 1,
      4, 4, 7, 4, 4, 7, 4, 4, 7, 4, 4, 7, 4, 4, 7, 4, 4, 7, 4, 4, 7, 4, 4, 7, 4, 4, 7, 4, 4, 7, 4, 4, 7, 4, 4, 7, 4, 4,
      7, 4, 4, 7, 4, 4, 7, 4, 4, 7, 4, 4, 7, 4, 4, 7, 4, 4, 7, 4, 4, 7, 4, 4, 7, 4, 4, 7, 4, 4, 7, 4, 4, 7, 4, 4, 7, 4,
      4, 1, 4, 4, 7, 4, 4, 7, 4, 4, 7, 4, 4, 7, 4, 4, 7, 4, 4, 7, 4, 4, 7, 4, 4, 7, 4, 4, 7, 4, 4, 1, 4, 4, 7, 4, 4, 7,
      4, 4, 7, 4, 4, 7, 4, 4, 1, 4, 4, 7, 4, 4, 7, 4, 4, 7, 4, 4, 7, 4, 4, 7, 4, 4, 1, 4, 4, 7, 4, 4, 7, 4, 4, 7, 4, 4,
      7, 4, 4, 7, 4, 4, 7, 4, 4, 7, 4, 4, 7, 4, 4, 7, 4, 4, 7, 4, 4, 7, 4, 4, 7, 4, 4, 7, 4, 4, 7, 4, 4, 7, 4, 4, 1, 4,
      4, 7, 4, 4, 7, 4, 4, 7, 4, 4, 7, 4, 4, 7, 4, 4, 7, 4, 4, 7, 4, 4, 7, 4, 4, 7, 4, 4, 7, 4, 4, 7, 4, 4, 7, 4, 4, 7,
      4, 4, 7, 4, 4, 7, 4, 4, 1, 4, 4, 1, 4, 4, 7, 4, 4, 7, 4, 4, 7, 4, 4, 7, 4, 4, 7, 4, 4, 7, 4, 4, 7, 4, 4, 7, 4, 4,
      7, 4, 4, 7, 4, 4, 7, 4, 4, 7, 4, 4, 7, 4, 4, 7, 4, 4, 7, 4, 4, 7
    ]
  },
  "plots": {
    "plotData": {
      "kmcTime": 2.0149328656054858e-5,
      "tof": [
        { "values": [5903.399732222341, 8153.172596184526] },
        { "values": [7871.199642963123, 8328.750042604812] }
      ],
      "coverage": [
        { "values": [0.0, 0.0, 0.005] },
        { "values": [0.0, 0.0, 0.07] },
        { "values": [0.0, 0.0, 0.0] },
        { "values": [0.0, 0.0, 0.0] },
        { "values": [0.99, 0.9925, 0.0] },
        { "values": [0.0075, 0.0, 0.0] },
        { "values": [0.0025, 0.0, 0.0] },
        { "values": [0.0, 0.0075, 0.925] }
      ]
    }
  }
}
